{
    "data": {
        "cargoes": [
            {
                "info": {
                    "color": "#470859",
                    "title": "Гофрокороб N25 (690х250х500)",
                    "article": "240",
                    "group_id": "14qjopsjt9ucv9a4gk6usn3ccogfckiw",
                    "group_title": "Группа 1"
                },
                "mass": 250.0,
                "size": {
                    "width": 800,
                    "height": 2095,
                    "length": 1200
                },
                "sort": 1,
                "type": "box",
                "count": 6,
                "margin": {
                    "width": 0,
                    "height": 0,
                    "length": 0
                },
                "cargo_id": "1emnfid2clh1lika2hsrm9fgeqzyleyh",
                "stacking": false,
                "turnover": false,
                "margin_width": 0,
                "margin_length": 0,
                "stacking_limit": 0
            },
            {
                "info": {
                    "color": "#85f7e5",
                    "title": "Гофрокороб N23 (565х380х495)",
                    "article": "240",
                    "group_id": "14qjopsjt9ucv9a4gk6usn3ccogfckiw",
                    "group_title": "Группа 1"
                },
                "mass": 250.0,
                "size": {
                    "width": 883,
                    "height": 2095,
                    "length": 1200
                },
                "sort": 1,
                "type": "box",
                "count": 2,
                "margin": {
                    "width": 0,
                    "height": 0,
                    "length": 0
                },
                "cargo_id": "g44yxlaijjtqhetpmsxxyphy3cy8nl0b",
                "stacking": false,
                "turnover": false,
                "margin_width": 0,
                "margin_length": 0,
                "stacking_limit": 0
            },
            {
                "info": {
                    "color": "#ccfe86",
                    "title": "Гофрокороб N17 (595х260х500)",
                    "article": "240",
                    "group_id": "14qjopsjt9ucv9a4gk6usn3ccogfckiw",
                    "group_title": "Группа 1"
                },
                "mass": 250.0,
                "size": {
                    "width": 800,
                    "height": 2095,
                    "length": 1200
                },
                "sort": 1,
                "type": "box",
                "count": 11,
                "margin": {
                    "width": 0,
                    "height": 0,
                    "length": 0
                },
                "cargo_id": "asnxixq2gx0axubxeg1quawx85qwugnr",
                "stacking": false,
                "turnover": false,
                "margin_width": 0,
                "margin_length": 0,
                "stacking_limit": 0
            },
            {
                "info": {
                    "color": "#b4bafc",
                    "title": "Гофрокороб N16 (585х290х525)",
                    "article": "240",
                    "group_id": "14qjopsjt9ucv9a4gk6usn3ccogfckiw",
                    "group_title": "Группа 1"
                },
                "mass": 250.0,
                "size": {
                    "width": 823,
                    "height": 2095,
                    "length": 1200
                },
                "sort": 1,
                "type": "box",
                "count": 6,
                "margin": {
                    "width": 0,
                    "height": 0,
                    "length": 0
                },
                "cargo_id": "y1mu21mnrmocfzoqqhtkxvd76nymnfug",
                "stacking": false,
                "turnover": false,
                "margin_width": 0,
                "margin_length": 0,
                "stacking_limit": 0
            },
            {
                "info": {
                    "color": "#843231",
                    "title": "Гофрокороб N15 (595х240х462)",
                    "article": "240",
                    "group_id": "14qjopsjt9ucv9a4gk6usn3ccogfckiw",
                    "group_title": "Группа 1"
                },
                "mass": 250.0,
                "size": {
                    "width": 800,
                    "height": 2095,
                    "length": 1200
                },
                "sort": 1,
                "type": "box",
                "count": 2,
                "margin": {
                    "width": 0,
                    "height": 0,
                    "length": 0
                },
                "cargo_id": "wanurdzfweuzri4zav8gchuf0lprrf0m",
                "stacking": false,
                "turnover": false,
                "margin_width": 0,
                "margin_length": 0,
                "stacking_limit": 0
            },
            {
                "info": {
                    "color": "#e75394",
                    "title": "Гофрокороб N8 (600х380х440)",
                    "article": "240",
                    "group_id": "14qjopsjt9ucv9a4gk6usn3ccogfckiw",
                    "group_title": "Группа 1"
                },
                "mass": 250.0,
                "size": {
                    "width": 828,
                    "height": 2095,
                    "length": 1200
                },
                "sort": 1,
                "type": "box",
                "count": 1,
                "margin": {
                    "width": 0,
                    "height": 0,
                    "length": 0
                },
                "cargo_id": "yeee452lj8cvwwd5czxknffmf3xraqrm",
                "stacking": false,
                "turnover": false,
                "margin_width": 0,
                "margin_length": 0,
                "stacking_limit": 0
            },
            {
                "info": {
                    "color": "#cb52a9",
                    "title": "Гофрокороб N3 (392х292х280)",
                    "article": "480",
                    "group_id": "14qjopsjt9ucv9a4gk6usn3ccogfckiw",
                    "group_title": "Группа 1"
                },
                "mass": 250.0,
                "size": {
                    "width": 800,
                    "height": 2095,
                    "length": 1200
                },
                "sort": 1,
                "type": "box",
                "count": 1,
                "margin": {
                    "width": 0,
                    "height": 0,
                    "length": 0
                },
                "cargo_id": "vhdvx3hlpoyzfjjv33rqqfin8oh9ihsr",
                "stacking": false,
                "turnover": false,
                "margin_width": 0,
                "margin_length": 0,
                "stacking_limit": 0
            },
            {
                "info": {
                    "color": "#6bbf58",
                    "title": "Гофрокороб N1 (600х380х500)",
                    "article": "240",
                    "group_id": "14qjopsjt9ucv9a4gk6usn3ccogfckiw",
                    "group_title": "Группа 1"
                },
                "mass": 250.0,
                "size": {
                    "width": 908,
                    "height": 2095,
                    "length": 1200
                },
                "sort": 1,
                "type": "box",
                "count": 2,
                "margin": {
                    "width": 0,
                    "height": 0,
                    "length": 0
                },
                "cargo_id": "knyyb7hp07me1mrzak2qcmeu0marvv1t",
                "stacking": false,
                "turnover": false,
                "margin_width": 0,
                "margin_length": 0,
                "stacking_limit": 0
            }
        ],
        "settings": {
            "rank": false,
            "max_step": 100,
            "min_step": 50,
            "usersort": false,
            "hardlimit": 1801,
            "timelimit": 1800,
            "step_scaling": 10
        },
        "put_boxes": [],
        "initial_id": 0,
        "cargo_space": {
            "id": 1319,
            "info": {
                "uid": "1319_0",
                "sort": 0,
                "title": "Фура Комус"
            },
            "mass": 9694,
            "size": {
                "width": 2400,
                "height": 2400,
                "length": 13300
            },
            "type": "truck",
            "axles": [
                {
                    "title": "Ось 1",
                    "distance": 2990,
                    "max_load": 11000,
                    "default_load": 2113
                },
                {
                    "title": "Ось 2",
                    "distance": 1360,
                    "max_load": 11000,
                    "default_load": 2090
                },
                {
                    "title": "Ось 3",
                    "distance": 1360,
                    "max_load": 11000,
                    "default_load": 2113
                }
            ],
            "hitch": {
                "title": "",
                "distance": 6240,
                "max_load": 10058,
                "default_load": 3378
            },
            "title": "Фура Комус",
            "tractor": {
                "mass": 7523,
                "axles": [
                    {
                        "title": "Ось 1",
                        "distance": 1475,
                        "max_load": 10000,
                        "default_load": 6013
                    },
                    {
                        "title": "Ось 2",
                        "distance": 3900,
                        "max_load": 11000,
                        "default_load": 4888
                    }
                ],
                "title": "Тягач MAN (Магнит)",
                "length": 7110,
                "hitch_distance": 885
            },
            "indentation": {
                "width": 0,
                "height": 0,
                "length": 0,
                "height_top": 0,
                "length_end": 0,
                "width_right": 0
            },
            "loading_size": {
                "width": 2400,
                "height": 2400,
                "length": 13300
            },
            "carrying_capacity": 24000,
            "last_changed_user_id": 3021
        },
        "calculation_id": "17373"
    },
    "data_result": {
        "boxes": [
            {
                "id": 30,
                "info": {
                    "color": "#6bbf58",
                    "title": "Гофрокороб N1 (600х380х500)",
                    "article": "240",
                    "group_id": "14qjopsjt9ucv9a4gk6usn3ccogfckiw",
                    "group_title": "Группа 1"
                },
                "mass": 250.0,
                "size": {
                    "width": 908.0,
                    "height": 2095.0,
                    "length": 1200.0
                },
                "sort": 1,
                "step": 1,
                "type": "box",
                "margin": {
                    "width": 0.0,
                    "height": 0.0,
                    "length": 0.0
                },
                "cargo_id": "knyyb7hp07me1mrzak2qcmeu0marvv1t",
                "position": {
                    "x": 0.0,
                    "y": 0.0,
                    "z": 1200.0
                },
                "stacking": false,
                "turnover": false,
                "rotation_state": 1,
                "stacking_limit": 0.0,
                "calculated_size": {
                    "width": 1200.0,
                    "height": 2095.0,
                    "length": 908.0
                },
                "virtual_positions": null
            },
            {
                "id": 29,
                "info": {
                    "color": "#6bbf58",
                    "title": "Гофрокороб N1 (600х380х500)",
                    "article": "240",
                    "group_id": "14qjopsjt9ucv9a4gk6usn3ccogfckiw",
                    "group_title": "Группа 1"
                },
                "mass": 250.0,
                "size": {
                    "width": 908.0,
                    "height": 2095.0,
                    "length": 1200.0
                },
                "sort": 1,
                "step": 2,
                "type": "box",
                "margin": {
                    "width": 0.0,
                    "height": 0.0,
                    "length": 0.0
                },
                "cargo_id": "knyyb7hp07me1mrzak2qcmeu0marvv1t",
                "position": {
                    "x": 0.0,
                    "y": 0.0,
                    "z": 0.0
                },
                "stacking": false,
                "turnover": false,
                "rotation_state": 1,
                "stacking_limit": 0.0,
                "calculated_size": {
                    "width": 1200.0,
                    "height": 2095.0,
                    "length": 908.0
                },
                "virtual_positions": null
            },
            {
                "id": 7,
                "info": {
                    "color": "#85f7e5",
                    "title": "Гофрокороб N23 (565х380х495)",
                    "article": "240",
                    "group_id": "14qjopsjt9ucv9a4gk6usn3ccogfckiw",
                    "group_title": "Группа 1"
                },
                "mass": 250.0,
                "size": {
                    "width": 883.0,
                    "height": 2095.0,
                    "length": 1200.0
                },
                "sort": 1,
                "step": 3,
                "type": "box",
                "margin": {
                    "width": 0.0,
                    "height": 0.0,
                    "length": 0.0
                },
                "cargo_id": "g44yxlaijjtqhetpmsxxyphy3cy8nl0b",
                "position": {
                    "x": 908.0,
                    "y": 0.0,
                    "z": 1200.0
                },
                "stacking": false,
                "turnover": false,
                "rotation_state": 1,
                "stacking_limit": 0.0,
                "calculated_size": {
                    "width": 1200.0,
                    "height": 2095.0,
                    "length": 883.0
                },
                "virtual_positions": null
            },
            {
                "id": 6,
                "info": {
                    "color": "#85f7e5",
                    "title": "Гофрокороб N23 (565х380х495)",
                    "article": "240",
                    "group_id": "14qjopsjt9ucv9a4gk6usn3ccogfckiw",
                    "group_title": "Группа 1"
                },
                "mass": 250.0,
                "size": {
                    "width": 883.0,
                    "height": 2095.0,
                    "length": 1200.0
                },
                "sort": 1,
                "step": 4,
                "type": "box",
                "margin": {
                    "width": 0.0,
                    "height": 0.0,
                    "length": 0.0
                },
                "cargo_id": "g44yxlaijjtqhetpmsxxyphy3cy8nl0b",
                "position": {
                    "x": 908.0,
                    "y": 0.0,
                    "z": 0.0
                },
                "stacking": false,
                "turnover": false,
                "rotation_state": 1,
                "stacking_limit": 0.0,
                "calculated_size": {
                    "width": 1200.0,
                    "height": 2095.0,
                    "length": 883.0
                },
                "virtual_positions": null
            },
            {
                "id": 19,
                "info": {
                    "color": "#b4bafc",
                    "title": "Гофрокороб N16 (585х290х525)",
                    "article": "240",
                    "group_id": "14qjopsjt9ucv9a4gk6usn3ccogfckiw",
                    "group_title": "Группа 1"
                },
                "mass": 250.0,
                "size": {
                    "width": 823.0,
                    "height": 2095.0,
                    "length": 1200.0
                },
                "sort": 1,
                "step": 5,
                "type": "box",
                "margin": {
                    "width": 0.0,
                    "height": 0.0,
                    "length": 0.0
                },
                "cargo_id": "y1mu21mnrmocfzoqqhtkxvd76nymnfug",
                "position": {
                    "x": 1791.0,
                    "y": 0.0,
                    "z": 1200.0
                },
                "stacking": false,
                "turnover": false,
                "rotation_state": 1,
                "stacking_limit": 0.0,
                "calculated_size": {
                    "width": 1200.0,
                    "height": 2095.0,
                    "length": 823.0
                },
                "virtual_positions": null
            },
            {
                "id": 27,
                "info": {
                    "color": "#e75394",
                    "title": "Гофрокороб N8 (600х380х440)",
                    "article": "240",
                    "group_id": "14qjopsjt9ucv9a4gk6usn3ccogfckiw",
                    "group_title": "Группа 1"
                },
                "mass": 250.0,
                "size": {
                    "width": 828.0,
                    "height": 2095.0,
                    "length": 1200.0
                },
                "sort": 1,
                "step": 6,
                "type": "box",
                "margin": {
                    "width": 0.0,
                    "height": 0.0,
                    "length": 0.0
                },
                "cargo_id": "yeee452lj8cvwwd5czxknffmf3xraqrm",
                "position": {
                    "x": 1791.0,
                    "y": 0.0,
                    "z": 0.0
                },
                "stacking": false,
                "turnover": false,
                "rotation_state": 1,
                "stacking_limit": 0.0,
                "calculated_size": {
                    "width": 1200.0,
                    "height": 2095.0,
                    "length": 828.0
                },
                "virtual_positions": null
            },
            {
                "id": 20,
                "info": {
                    "color": "#b4bafc",
                    "title": "Гофрокороб N16 (585х290х525)",
                    "article": "240",
                    "group_id": "14qjopsjt9ucv9a4gk6usn3ccogfckiw",
                    "group_title": "Группа 1"
                },
                "mass": 250.0,
                "size": {
                    "width": 823.0,
                    "height": 2095.0,
                    "length": 1200.0
                },
                "sort": 1,
                "step": 7,
                "type": "box",
                "margin": {
                    "width": 0.0,
                    "height": 0.0,
                    "length": 0.0
                },
                "cargo_id": "y1mu21mnrmocfzoqqhtkxvd76nymnfug",
                "position": {
                    "x": 2614.0,
                    "y": 0.0,
                    "z": 1200.0
                },
                "stacking": false,
                "turnover": false,
                "rotation_state": 1,
                "stacking_limit": 0.0,
                "calculated_size": {
                    "width": 1200.0,
                    "height": 2095.0,
                    "length": 823.0
                },
                "virtual_positions": null
            },
            {
                "id": 21,
                "info": {
                    "color": "#b4bafc",
                    "title": "Гофрокороб N16 (585х290х525)",
                    "article": "240",
                    "group_id": "14qjopsjt9ucv9a4gk6usn3ccogfckiw",
                    "group_title": "Группа 1"
                },
                "mass": 250.0,
                "size": {
                    "width": 823.0,
                    "height": 2095.0,
                    "length": 1200.0
                },
                "sort": 1,
                "step": 8,
                "type": "box",
                "margin": {
                    "width": 0.0,
                    "height": 0.0,
                    "length": 0.0
                },
                "cargo_id": "y1mu21mnrmocfzoqqhtkxvd76nymnfug",
                "position": {
                    "x": 2619.0,
                    "y": 0.0,
                    "z": 0.0
                },
                "stacking": false,
                "turnover": false,
                "rotation_state": 1,
                "stacking_limit": 0.0,
                "calculated_size": {
                    "width": 1200.0,
                    "height": 2095.0,
                    "length": 823.0
                },
                "virtual_positions": null
            },
            {
                "id": 22,
                "info": {
                    "color": "#b4bafc",
                    "title": "Гофрокороб N16 (585х290х525)",
                    "article": "240",
                    "group_id": "14qjopsjt9ucv9a4gk6usn3ccogfckiw",
                    "group_title": "Группа 1"
                },
                "mass": 250.0,
                "size": {
                    "width": 823.0,
                    "height": 2095.0,
                    "length": 1200.0
                },
                "sort": 1,
                "step": 9,
                "type": "box",
                "margin": {
                    "width": 0.0,
                    "height": 0.0,
                    "length": 0.0
                },
                "cargo_id": "y1mu21mnrmocfzoqqhtkxvd76nymnfug",
                "position": {
                    "x": 3437.0,
                    "y": 0.0,
                    "z": 1200.0
                },
                "stacking": false,
                "turnover": false,
                "rotation_state": 1,
                "stacking_limit": 0.0,
                "calculated_size": {
                    "width": 1200.0,
                    "height": 2095.0,
                    "length": 823.0
                },
                "virtual_positions": null
            },
            {
                "id": 23,
                "info": {
                    "color": "#b4bafc",
                    "title": "Гофрокороб N16 (585х290х525)",
                    "article": "240",
                    "group_id": "14qjopsjt9ucv9a4gk6usn3ccogfckiw",
                    "group_title": "Группа 1"
                },
                "mass": 250.0,
                "size": {
                    "width": 823.0,
                    "height": 2095.0,
                    "length": 1200.0
                },
                "sort": 1,
                "step": 10,
                "type": "box",
                "margin": {
                    "width": 0.0,
                    "height": 0.0,
                    "length": 0.0
                },
                "cargo_id": "y1mu21mnrmocfzoqqhtkxvd76nymnfug",
                "position": {
                    "x": 3442.0,
                    "y": 0.0,
                    "z": 0.0
                },
                "stacking": false,
                "turnover": false,
                "rotation_state": 1,
                "stacking_limit": 0.0,
                "calculated_size": {
                    "width": 1200.0,
                    "height": 2095.0,
                    "length": 823.0
                },
                "virtual_positions": null
            },
            {
                "id": 24,
                "info": {
                    "color": "#b4bafc",
                    "title": "Гофрокороб N16 (585х290х525)",
                    "article": "240",
                    "group_id": "14qjopsjt9ucv9a4gk6usn3ccogfckiw",
                    "group_title": "Группа 1"
                },
                "mass": 250.0,
                "size": {
                    "width": 823.0,
                    "height": 2095.0,
                    "length": 1200.0
                },
                "sort": 1,
                "step": 11,
                "type": "box",
                "margin": {
                    "width": 0.0,
                    "height": 0.0,
                    "length": 0.0
                },
                "cargo_id": "y1mu21mnrmocfzoqqhtkxvd76nymnfug",
                "position": {
                    "x": 4260.0,
                    "y": 0.0,
                    "z": 1200.0
                },
                "stacking": false,
                "turnover": false,
                "rotation_state": 1,
                "stacking_limit": 0.0,
                "calculated_size": {
                    "width": 1200.0,
                    "height": 2095.0,
                    "length": 823.0
                },
                "virtual_positions": null
            },
            {
                "id": 0,
                "info": {
                    "color": "#470859",
                    "title": "Гофрокороб N25 (690х250х500)",
                    "article": "240",
                    "group_id": "14qjopsjt9ucv9a4gk6usn3ccogfckiw",
                    "group_title": "Группа 1"
                },
                "mass": 250.0,
                "size": {
                    "width": 800.0,
                    "height": 2095.0,
                    "length": 1200.0
                },
                "sort": 1,
                "step": 12,
                "type": "box",
                "margin": {
                    "width": 0.0,
                    "height": 0.0,
                    "length": 0.0
                },
                "cargo_id": "1emnfid2clh1lika2hsrm9fgeqzyleyh",
                "position": {
                    "x": 4265.0,
                    "y": 0.0,
                    "z": 0.0
                },
                "stacking": false,
                "turnover": false,
                "rotation_state": 1,
                "stacking_limit": 0.0,
                "calculated_size": {
                    "width": 1200.0,
                    "height": 2095.0,
                    "length": 800.0
                },
                "virtual_positions": null
            },
            {
                "id": 2,
                "info": {
                    "color": "#470859",
                    "title": "Гофрокороб N25 (690х250х500)",
                    "article": "240",
                    "group_id": "14qjopsjt9ucv9a4gk6usn3ccogfckiw",
                    "group_title": "Группа 1"
                },
                "mass": 250.0,
                "size": {
                    "width": 800.0,
                    "height": 2095.0,
                    "length": 1200.0
                },
                "sort": 1,
                "step": 13,
                "type": "box",
                "margin": {
                    "width": 0.0,
                    "height": 0.0,
                    "length": 0.0
                },
                "cargo_id": "1emnfid2clh1lika2hsrm9fgeqzyleyh",
                "position": {
                    "x": 5083.0,
                    "y": 0.0,
                    "z": 1200.0
                },
                "stacking": false,
                "turnover": false,
                "rotation_state": 1,
                "stacking_limit": 0.0,
                "calculated_size": {
                    "width": 1200.0,
                    "height": 2095.0,
                    "length": 800.0
                },
                "virtual_positions": null
            },
            {
                "id": 1,
                "info": {
                    "color": "#470859",
                    "title": "Гофрокороб N25 (690х250х500)",
                    "article": "240",
                    "group_id": "14qjopsjt9ucv9a4gk6usn3ccogfckiw",
                    "group_title": "Группа 1"
                },
                "mass": 250.0,
                "size": {
                    "width": 800.0,
                    "height": 2095.0,
                    "length": 1200.0
                },
                "sort": 1,
                "step": 14,
                "type": "box",
                "margin": {
                    "width": 0.0,
                    "height": 0.0,
                    "length": 0.0
                },
                "cargo_id": "1emnfid2clh1lika2hsrm9fgeqzyleyh",
                "position": {
                    "x": 5065.0,
                    "y": 0.0,
                    "z": 0.0
                },
                "stacking": false,
                "turnover": false,
                "rotation_state": 1,
                "stacking_limit": 0.0,
                "calculated_size": {
                    "width": 1200.0,
                    "height": 2095.0,
                    "length": 800.0
                },
                "virtual_positions": null
            },
            {
                "id": 4,
                "info": {
                    "color": "#470859",
                    "title": "Гофрокороб N25 (690х250х500)",
                    "article": "240",
                    "group_id": "14qjopsjt9ucv9a4gk6usn3ccogfckiw",
                    "group_title": "Группа 1"
                },
                "mass": 250.0,
                "size": {
                    "width": 800.0,
                    "height": 2095.0,
                    "length": 1200.0
                },
                "sort": 1,
                "step": 15,
                "type": "box",
                "margin": {
                    "width": 0.0,
                    "height": 0.0,
                    "length": 0.0
                },
                "cargo_id": "1emnfid2clh1lika2hsrm9fgeqzyleyh",
                "position": {
                    "x": 5883.0,
                    "y": 0.0,
                    "z": 1200.0
                },
                "stacking": false,
                "turnover": false,
                "rotation_state": 1,
                "stacking_limit": 0.0,
                "calculated_size": {
                    "width": 1200.0,
                    "height": 2095.0,
                    "length": 800.0
                },
                "virtual_positions": null
            },
            {
                "id": 3,
                "info": {
                    "color": "#470859",
                    "title": "Гофрокороб N25 (690х250х500)",
                    "article": "240",
                    "group_id": "14qjopsjt9ucv9a4gk6usn3ccogfckiw",
                    "group_title": "Группа 1"
                },
                "mass": 250.0,
                "size": {
                    "width": 800.0,
                    "height": 2095.0,
                    "length": 1200.0
                },
                "sort": 1,
                "step": 16,
                "type": "box",
                "margin": {
                    "width": 0.0,
                    "height": 0.0,
                    "length": 0.0
                },
                "cargo_id": "1emnfid2clh1lika2hsrm9fgeqzyleyh",
                "position": {
                    "x": 5865.0,
                    "y": 0.0,
                    "z": 0.0
                },
                "stacking": false,
                "turnover": false,
                "rotation_state": 1,
                "stacking_limit": 0.0,
                "calculated_size": {
                    "width": 1200.0,
                    "height": 2095.0,
                    "length": 800.0
                },
                "virtual_positions": null
            },
            {
                "id": 8,
                "info": {
                    "color": "#ccfe86",
                    "title": "Гофрокороб N17 (595х260х500)",
                    "article": "240",
                    "group_id": "14qjopsjt9ucv9a4gk6usn3ccogfckiw",
                    "group_title": "Группа 1"
                },
                "mass": 250.0,
                "size": {
                    "width": 800.0,
                    "height": 2095.0,
                    "length": 1200.0
                },
                "sort": 1,
                "step": 17,
                "type": "box",
                "margin": {
                    "width": 0.0,
                    "height": 0.0,
                    "length": 0.0
                },
                "cargo_id": "asnxixq2gx0axubxeg1quawx85qwugnr",
                "position": {
                    "x": 6683.0,
                    "y": 0.0,
                    "z": 1200.0
                },
                "stacking": false,
                "turnover": false,
                "rotation_state": 1,
                "stacking_limit": 0.0,
                "calculated_size": {
                    "width": 1200.0,
                    "height": 2095.0,
                    "length": 800.0
                },
                "virtual_positions": null
            },
            {
                "id": 5,
                "info": {
                    "color": "#470859",
                    "title": "Гофрокороб N25 (690х250х500)",
                    "article": "240",
                    "group_id": "14qjopsjt9ucv9a4gk6usn3ccogfckiw",
                    "group_title": "Группа 1"
                },
                "mass": 250.0,
                "size": {
                    "width": 800.0,
                    "height": 2095.0,
                    "length": 1200.0
                },
                "sort": 1,
                "step": 18,
                "type": "box",
                "margin": {
                    "width": 0.0,
                    "height": 0.0,
                    "length": 0.0
                },
                "cargo_id": "1emnfid2clh1lika2hsrm9fgeqzyleyh",
                "position": {
                    "x": 6665.0,
                    "y": 0.0,
                    "z": 0.0
                },
                "stacking": false,
                "turnover": false,
                "rotation_state": 1,
                "stacking_limit": 0.0,
                "calculated_size": {
                    "width": 1200.0,
                    "height": 2095.0,
                    "length": 800.0
                },
                "virtual_positions": null
            },
            {
                "id": 10,
                "info": {
                    "color": "#ccfe86",
                    "title": "Гофрокороб N17 (595х260х500)",
                    "article": "240",
                    "group_id": "14qjopsjt9ucv9a4gk6usn3ccogfckiw",
                    "group_title": "Группа 1"
                },
                "mass": 250.0,
                "size": {
                    "width": 800.0,
                    "height": 2095.0,
                    "length": 1200.0
                },
                "sort": 1,
                "step": 19,
                "type": "box",
                "margin": {
                    "width": 0.0,
                    "height": 0.0,
                    "length": 0.0
                },
                "cargo_id": "asnxixq2gx0axubxeg1quawx85qwugnr",
                "position": {
                    "x": 7483.0,
                    "y": 0.0,
                    "z": 1200.0
                },
                "stacking": false,
                "turnover": false,
                "rotation_state": 1,
                "stacking_limit": 0.0,
                "calculated_size": {
                    "width": 1200.0,
                    "height": 2095.0,
                    "length": 800.0
                },
                "virtual_positions": null
            },
            {
                "id": 9,
                "info": {
                    "color": "#ccfe86",
                    "title": "Гофрокороб N17 (595х260х500)",
                    "article": "240",
                    "group_id": "14qjopsjt9ucv9a4gk6usn3ccogfckiw",
                    "group_title": "Группа 1"
                },
                "mass": 250.0,
                "size": {
                    "width": 800.0,
                    "height": 2095.0,
                    "length": 1200.0
                },
                "sort": 1,
                "step": 20,
                "type": "box",
                "margin": {
                    "width": 0.0,
                    "height": 0.0,
                    "length": 0.0
                },
                "cargo_id": "asnxixq2gx0axubxeg1quawx85qwugnr",
                "position": {
                    "x": 7465.0,
                    "y": 0.0,
                    "z": 0.0
                },
                "stacking": false,
                "turnover": false,
                "rotation_state": 1,
                "stacking_limit": 0.0,
                "calculated_size": {
                    "width": 1200.0,
                    "height": 2095.0,
                    "length": 800.0
                },
                "virtual_positions": null
            },
            {
                "id": 12,
                "info": {
                    "color": "#ccfe86",
                    "title": "Гофрокороб N17 (595х260х500)",
                    "article": "240",
                    "group_id": "14qjopsjt9ucv9a4gk6usn3ccogfckiw",
                    "group_title": "Группа 1"
                },
                "mass": 250.0,
                "size": {
                    "width": 800.0,
                    "height": 2095.0,
                    "length": 1200.0
                },
                "sort": 1,
                "step": 21,
                "type": "box",
                "margin": {
                    "width": 0.0,
                    "height": 0.0,
                    "length": 0.0
                },
                "cargo_id": "asnxixq2gx0axubxeg1quawx85qwugnr",
                "position": {
                    "x": 8283.0,
                    "y": 0.0,
                    "z": 1200.0
                },
                "stacking": false,
                "turnover": false,
                "rotation_state": 1,
                "stacking_limit": 0.0,
                "calculated_size": {
                    "width": 1200.0,
                    "height": 2095.0,
                    "length": 800.0
                },
                "virtual_positions": null
            },
            {
                "id": 11,
                "info": {
                    "color": "#ccfe86",
                    "title": "Гофрокороб N17 (595х260х500)",
                    "article": "240",
                    "group_id": "14qjopsjt9ucv9a4gk6usn3ccogfckiw",
                    "group_title": "Группа 1"
                },
                "mass": 250.0,
                "size": {
                    "width": 800.0,
                    "height": 2095.0,
                    "length": 1200.0
                },
                "sort": 1,
                "step": 22,
                "type": "box",
                "margin": {
                    "width": 0.0,
                    "height": 0.0,
                    "length": 0.0
                },
                "cargo_id": "asnxixq2gx0axubxeg1quawx85qwugnr",
                "position": {
                    "x": 8265.0,
                    "y": 0.0,
                    "z": 0.0
                },
                "stacking": false,
                "turnover": false,
                "rotation_state": 1,
                "stacking_limit": 0.0,
                "calculated_size": {
                    "width": 1200.0,
                    "height": 2095.0,
                    "length": 800.0
                },
                "virtual_positions": null
            },
            {
                "id": 14,
                "info": {
                    "color": "#ccfe86",
                    "title": "Гофрокороб N17 (595х260х500)",
                    "article": "240",
                    "group_id": "14qjopsjt9ucv9a4gk6usn3ccogfckiw",
                    "group_title": "Группа 1"
                },
                "mass": 250.0,
                "size": {
                    "width": 800.0,
                    "height": 2095.0,
                    "length": 1200.0
                },
                "sort": 1,
                "step": 23,
                "type": "box",
                "margin": {
                    "width": 0.0,
                    "height": 0.0,
                    "length": 0.0
                },
                "cargo_id": "asnxixq2gx0axubxeg1quawx85qwugnr",
                "position": {
                    "x": 9083.0,
                    "y": 0.0,
                    "z": 1200.0
                },
                "stacking": false,
                "turnover": false,
                "rotation_state": 1,
                "stacking_limit": 0.0,
                "calculated_size": {
                    "width": 1200.0,
                    "height": 2095.0,
                    "length": 800.0
                },
                "virtual_positions": null
            },
            {
                "id": 13,
                "info": {
                    "color": "#ccfe86",
                    "title": "Гофрокороб N17 (595х260х500)",
                    "article": "240",
                    "group_id": "14qjopsjt9ucv9a4gk6usn3ccogfckiw",
                    "group_title": "Группа 1"
                },
                "mass": 250.0,
                "size": {
                    "width": 800.0,
                    "height": 2095.0,
                    "length": 1200.0
                },
                "sort": 1,
                "step": 24,
                "type": "box",
                "margin": {
                    "width": 0.0,
                    "height": 0.0,
                    "length": 0.0
                },
                "cargo_id": "asnxixq2gx0axubxeg1quawx85qwugnr",
                "position": {
                    "x": 9065.0,
                    "y": 0.0,
                    "z": 0.0
                },
                "stacking": false,
                "turnover": false,
                "rotation_state": 1,
                "stacking_limit": 0.0,
                "calculated_size": {
                    "width": 1200.0,
                    "height": 2095.0,
                    "length": 800.0
                },
                "virtual_positions": null
            },
            {
                "id": 16,
                "info": {
                    "color": "#ccfe86",
                    "title": "Гофрокороб N17 (595х260х500)",
                    "article": "240",
                    "group_id": "14qjopsjt9ucv9a4gk6usn3ccogfckiw",
                    "group_title": "Группа 1"
                },
                "mass": 250.0,
                "size": {
                    "width": 800.0,
                    "height": 2095.0,
                    "length": 1200.0
                },
                "sort": 1,
                "step": 25,
                "type": "box",
                "margin": {
                    "width": 0.0,
                    "height": 0.0,
                    "length": 0.0
                },
                "cargo_id": "asnxixq2gx0axubxeg1quawx85qwugnr",
                "position": {
                    "x": 9883.0,
                    "y": 0.0,
                    "z": 1200.0
                },
                "stacking": false,
                "turnover": false,
                "rotation_state": 1,
                "stacking_limit": 0.0,
                "calculated_size": {
                    "width": 1200.0,
                    "height": 2095.0,
                    "length": 800.0
                },
                "virtual_positions": null
            },
            {
                "id": 15,
                "info": {
                    "color": "#ccfe86",
                    "title": "Гофрокороб N17 (595х260х500)",
                    "article": "240",
                    "group_id": "14qjopsjt9ucv9a4gk6usn3ccogfckiw",
                    "group_title": "Группа 1"
                },
                "mass": 250.0,
                "size": {
                    "width": 800.0,
                    "height": 2095.0,
                    "length": 1200.0
                },
                "sort": 1,
                "step": 26,
                "type": "box",
                "margin": {
                    "width": 0.0,
                    "height": 0.0,
                    "length": 0.0
                },
                "cargo_id": "asnxixq2gx0axubxeg1quawx85qwugnr",
                "position": {
                    "x": 9865.0,
                    "y": 0.0,
                    "z": 0.0
                },
                "stacking": false,
                "turnover": false,
                "rotation_state": 1,
                "stacking_limit": 0.0,
                "calculated_size": {
                    "width": 1200.0,
                    "height": 2095.0,
                    "length": 800.0
                },
                "virtual_positions": null
            },
            {
                "id": 18,
                "info": {
                    "color": "#ccfe86",
                    "title": "Гофрокороб N17 (595х260х500)",
                    "article": "240",
                    "group_id": "14qjopsjt9ucv9a4gk6usn3ccogfckiw",
                    "group_title": "Группа 1"
                },
                "mass": 250.0,
                "size": {
                    "width": 800.0,
                    "height": 2095.0,
                    "length": 1200.0
                },
                "sort": 1,
                "step": 27,
                "type": "box",
                "margin": {
                    "width": 0.0,
                    "height": 0.0,
                    "length": 0.0
                },
                "cargo_id": "asnxixq2gx0axubxeg1quawx85qwugnr",
                "position": {
                    "x": 10683.0,
                    "y": 0.0,
                    "z": 1200.0
                },
                "stacking": false,
                "turnover": false,
                "rotation_state": 1,
                "stacking_limit": 0.0,
                "calculated_size": {
                    "width": 1200.0,
                    "height": 2095.0,
                    "length": 800.0
                },
                "virtual_positions": null
            },
            {
                "id": 17,
                "info": {
                    "color": "#ccfe86",
                    "title": "Гофрокороб N17 (595х260х500)",
                    "article": "240",
                    "group_id": "14qjopsjt9ucv9a4gk6usn3ccogfckiw",
                    "group_title": "Группа 1"
                },
                "mass": 250.0,
                "size": {
                    "width": 800.0,
                    "height": 2095.0,
                    "length": 1200.0
                },
                "sort": 1,
                "step": 28,
                "type": "box",
                "margin": {
                    "width": 0.0,
                    "height": 0.0,
                    "length": 0.0
                },
                "cargo_id": "asnxixq2gx0axubxeg1quawx85qwugnr",
                "position": {
                    "x": 10665.0,
                    "y": 0.0,
                    "z": 0.0
                },
                "stacking": false,
                "turnover": false,
                "rotation_state": 1,
                "stacking_limit": 0.0,
                "calculated_size": {
                    "width": 1200.0,
                    "height": 2095.0,
                    "length": 800.0
                },
                "virtual_positions": null
            },
            {
                "id": 26,
                "info": {
                    "color": "#843231",
                    "title": "Гофрокороб N15 (595х240х462)",
                    "article": "240",
                    "group_id": "14qjopsjt9ucv9a4gk6usn3ccogfckiw",
                    "group_title": "Группа 1"
                },
                "mass": 250.0,
                "size": {
                    "width": 800.0,
                    "height": 2095.0,
                    "length": 1200.0
                },
                "sort": 1,
                "step": 29,
                "type": "box",
                "margin": {
                    "width": 0.0,
                    "height": 0.0,
                    "length": 0.0
                },
                "cargo_id": "wanurdzfweuzri4zav8gchuf0lprrf0m",
                "position": {
                    "x": 11483.0,
                    "y": 0.0,
                    "z": 1200.0
                },
                "stacking": false,
                "turnover": false,
                "rotation_state": 1,
                "stacking_limit": 0.0,
                "calculated_size": {
                    "width": 1200.0,
                    "height": 2095.0,
                    "length": 800.0
                },
                "virtual_positions": null
            },
            {
                "id": 25,
                "info": {
                    "color": "#843231",
                    "title": "Гофрокороб N15 (595х240х462)",
                    "article": "240",
                    "group_id": "14qjopsjt9ucv9a4gk6usn3ccogfckiw",
                    "group_title": "Группа 1"
                },
                "mass": 250.0,
                "size": {
                    "width": 800.0,
                    "height": 2095.0,
                    "length": 1200.0
                },
                "sort": 1,
                "step": 30,
                "type": "box",
                "margin": {
                    "width": 0.0,
                    "height": 0.0,
                    "length": 0.0
                },
                "cargo_id": "wanurdzfweuzri4zav8gchuf0lprrf0m",
                "position": {
                    "x": 11465.0,
                    "y": 0.0,
                    "z": 0.0
                },
                "stacking": false,
                "turnover": false,
                "rotation_state": 1,
                "stacking_limit": 0.0,
                "calculated_size": {
                    "width": 1200.0,
                    "height": 2095.0,
                    "length": 800.0
                },
                "virtual_positions": null
            },
            {
                "id": 28,
                "info": {
                    "color": "#cb52a9",
                    "title": "Гофрокороб N3 (392х292х280)",
                    "article": "480",
                    "group_id": "14qjopsjt9ucv9a4gk6usn3ccogfckiw",
                    "group_title": "Группа 1"
                },
                "mass": 250.0,
                "size": {
                    "width": 800.0,
                    "height": 2095.0,
                    "length": 1200.0
                },
                "sort": 1,
                "step": 31,
                "type": "box",
                "margin": {
                    "width": 0.0,
                    "height": 0.0,
                    "length": 0.0
                },
                "cargo_id": "vhdvx3hlpoyzfjjv33rqqfin8oh9ihsr",
                "position": {
                    "x": 12265.0,
                    "y": 0.0,
                    "z": 0.0
                },
                "stacking": false,
                "turnover": false,
                "rotation_state": 1,
                "stacking_limit": 0.0,
                "calculated_size": {
                    "width": 1200.0,
                    "height": 2095.0,
                    "length": 800.0
                },
                "virtual_positions": null
            }
        ],
        "version": 5,
        "cargo_space": {
            "id": 1319,
            "info": {
                "uid": "1319_0",
                "sort": 0,
                "title": "Фура Комус"
            },
            "mass": 9694.0,
            "size": {
                "width": 2400.0,
                "height": 2400.0,
                "length": 13300.0
            },
            "type": "truck",
            "axles": [
                {
                    "title": "Ось 1",
                    "distance": 2990.0,
                    "max_load": 11000.0,
                    "default_load": 2113.0,
                    "calculated_load": 4788.74065
                },
                {
                    "title": "Ось 2",
                    "distance": 1360.0,
                    "max_load": 11000.0,
                    "default_load": 2090.0,
                    "calculated_load": 4765.74065
                },
                {
                    "title": "Ось 3",
                    "distance": 1360.0,
                    "max_load": 11000.0,
                    "default_load": 2113.0,
                    "calculated_load": 4788.74065
                }
            ],
            "hitch": {
                "title": "",
                "distance": 6240.0,
                "max_load": 10058.0,
                "default_load": 3378.0,
                "calculated_load": 3100.77806
            },
            "tractor": {
                "mass": 7523.0,
                "axles": [
                    {
                        "title": "Ось 1",
                        "distance": 1475.0,
                        "max_load": 10000.0,
                        "default_load": 6013.0,
                        "calculated_load": 5950.09194
                    },
                    {
                        "title": "Ось 2",
                        "distance": 3900.0,
                        "max_load": 11000.0,
                        "default_load": 4888.0,
                        "calculated_load": 4673.68612
                    }
                ],
                "length": 7110.0,
                "hitch_distance": 885.0
            },
            "full_length": 13300.0,
            "indentation": {
                "width": 0.0,
                "height": 0.0,
                "length": 0.0,
                "height_top": 0.0,
                "length_end": 0.0,
                "width_right": 0.0
            },
            "loading_size": {
                "width": 2400.0,
                "height": 2400.0,
                "length": 13300.0
            },
            "calculation_info": {
                "step_count": 31,
                "cargos_mass": 7.75,
                "load_volume": 76.608,
                "cargos_volume": 63.72487,
                "count_cargoes": 31,
                "load_capacity": 24.0,
                "loading_height": 2.095,
                "density_percent": 97.00727,
                "remaining_volume": 12.88313,
                "void_space_percent": 16.81695,
                "filling_space_percent": 83.18305
            },
            "carrying_capacity": 24000.0,
            "real_center_of_gravity": [
                6448.580645161291,
                1047.5,
                1180.6451612903227
            ],
            "ideal_center_of_gravity": [
                6650.0,
                0.0,
                1200.0
            ]
        },
        "cargo_groups": [],
        "packing_type": "PackingTruck PackingTwoBoxesInLayer",
        "calculation_id": 17373,
        "invalid_errors": [],
        "unpacked_errors": [],
        "validate_errors": [],
        "is_packed_same_boxes": false
    }
}